tests/__init__.py
tests/test_core.py
xmlrecords/__init__.py
xmlrecords/src/__init__.py
xmlrecords/src/xmlrecords.py
xmlrecords-0.3.1.dist-info/LICENSE
xmlrecords-0.3.1.dist-info/METADATA
xmlrecords-0.3.1.dist-info/WHEEL
xmlrecords-0.3.1.dist-info/top_level.txt
xmlrecords-0.3.1.dist-info/RECORD
