Metadata-Version: 2.1
Name: xmlrecords
Version: 0.3.1
Summary: This package can convert an XML files to a list of records
Home-page: UNKNOWN
Author: Yaroslav Kopotilov
Author-email: datascience@tuta.io
License: Apache License, Version 2.0
Keywords: xml parsing
Platform: UNKNOWN
Classifier: Intended Audience :: Developers
Classifier: License :: OSI Approved :: Apache Software License
Classifier: Operating System :: OS Independent
Classifier: Programming Language :: Python
Classifier: Programming Language :: Python :: 3.8
Classifier: Programming Language :: Python :: 3.9
Classifier: Topic :: Software Development :: Libraries :: Python Modules
Requires-Python: >=3.7
Requires-Dist: lxml
